project/verilog/flipflop.v
`timescale 1ns / 1ps

module ffo(D, clk, Q, Qbar);

  input D; 
  input clk; 
  output Q;
  output Qbar;

  wire clknot, Dnot, o1, o2, o3, o4, o5, o6;

  assign clknot = ~clk;
  assign Dnot = ~D;
  assign o1 = ~(D & clknot);
  assign o2 = ~(Dnot & clknot);
  assign o3 = ~(o1 & o4);
  assign o4 = ~(o2 & o3);
  assign o5 = ~(o3 & clk);
  assign o6 = ~(o4 & clk);
  assign Q = ~(o5 & Qbar);
  assign Qbar = ~(o6 & Q);

endmodule

module ffi(D, clk, Q, Qbar);

  input D; 
  input clk; 
  output Q;
  output Qbar;

  wire clknot, Dnot, o1, o2, o3, o4, o5, o6;

  assign clknot = ~clk;
  assign Dnot = ~D;
  assign o1 = ~(D & clk);
  assign o2 = ~(Dnot & clk);
  assign o3 = ~(o1 & o4);
  assign o4 = ~(o2 & o3);
  assign o5 = ~(o3 & clknot);
  assign o6 = ~(o4 & clknot);
  assign Q = ~(o5 & Qbar);
  assign Qbar = ~(o6 & Q);

endmodule

module ff(D, clk, Q, Qbar);

  input D; 
  input clk; 
  output Q;
  output Qbar;

  wire clknot, Dnot, o1, o2, o3, o4, o5, o6;

  assign clknot = ~clk;
  assign Dnot = ~D;
  assign o1 = ~(D & clk);
  assign o2 = ~(Dnot & clk);
  assign o3 = ~(o1 & o4);
  assign o4 = ~(o2 & o3);
  assign o5 = ~(o3 & clk);
  assign o6 = ~(o4 & clk);
  assign Q = ~(o5 & Qbar);
  assign Qbar = ~(o6 & Q);

endmodule

project/verilog/pg.v
`timescale 1ns / 1ps

module pg( x,y,p,g);
  
  input x;
  input y;
  output p;
  output g;


  and and1(g,x,y);
  xor xor1(p,x,y);

endmodule

project/verilog/carry.v
`timescale 1ns / 1ps

`include "pg.v"

module cla(x1, x2, x3, x4, y1, y2, y3, y4, cin, z1, z2, z3, z4, cout);
  input x1, x2, x3, x4, y1, y2, y3, y4, cin;
  output z1, z2, z3, z4, cout;

  wire p1, p2, p3, p4;
  wire g1, g2, g3, g4;

  wire c1, c2, c3;

  
  pg pg1(x1, y1, p1, g1);
  pg pg2(x2, y2, p2, g2);
  pg pg3(x3, y3, p3, g3);
  pg pg4(x4, y4, p4, g4);

 
  assign c1 = g1 | (p1 & cin);
  assign c2 = g2 | (p2 & c1);
  assign c3 = g3 | (p3 & c2);
  assign cout = g4 | (p4 & c3);


  assign z1 = p1 ^ cin;
  assign z2 = p2 ^ c1;
  assign z3 = p3 ^ c2;
  assign z4 = p4 ^ c3;
endmodule

project/verilog/final.v
`timescale 1ns / 1ps

`include "carry.v"
`include "flipflop.v"

module toplevel(clk,x,y,cin,cout,z);
  
  input clk;
  input [4:1] x;
  input [4:1] y;
  input cin;
  
  output cout;
  output [4:1] z;

  wire x1in;
  wire x2in;
  wire x3in;
  wire x4in;
  wire y1in;
  wire y2in;
  wire y3in;
  wire y4in;

  wire coutoo;

  wire z1o;
  wire z2o;
  wire z3o;
  wire z4o;


  ffi  ffcin(
    .D  (cin),
    .clk(clk),
    .Q  (cinin)
  );

  ffi  ffx1(
    .D  (x[1]),
    .clk(clk),
    .Q  (x1in)
  );

  ffi  ffx2(
    .D  (x[2]),
    .clk(clk),
    .Q  (x2in)
  );

  ffi  ffx3(
    .D  (x[3]),
    .clk(clk),
    .Q  (x3in)
  );

  ffi  ffx4(
    .D  (x[4]),
    .clk(clk),
    .Q  (x4in)
  );

  ffi  ffy1(
    .D  (y[1]),
    .clk(clk),
    .Q  (y1in)
  );

  ffi  ffy2(
    .D  (y[2]),
    .clk(clk),
    .Q  (y2in)
  );

  ffi  ffy3(
    .D  (y[3]),
    .clk(clk),
    .Q  (y3in)
  );

  ffi  ffy4(
    .D  (y[4]),
    .clk(clk),
    .Q  (y4in)
  );
  
  
  cla cla1(
    .x1  (x1in),
    .x2  (x2in),
    .x3  (x3in),
    .x4  (x4in),
    .y1  (y1in),
    .y2  (y2in),
    .y3  (y3in),
    .y4  (y4in),
    .cin (cinin),
    .z1  (z1o ),
    .z2  (z2o ),
    .z3  (z3o ),
    .z4  (z4o ),
    .cout(coutoo)
  );

  ffo  ffz1(
    .D  (z1o),
    .clk(clk),
    .Q  (z[1])
  );

  ffo ffz2(
    .D  (z2o),
    .clk(clk),
    .Q  (z[2])
  );

  ffo  ffz3(
    .D  (z3o),
    .clk(clk),
    .Q  (z[3])
  );

  ffo  ffz4(
    .D  (z4o),
    .clk(clk),
    .Q  (z[4])
  );

  ffo ffcout(
    .D  (coutoo),
    .clk(clk),
    .Q  (cout)
  );
  
endmodule

project/verilog/final_tb.v

`timescale 1ns / 1ps

module tb;

  reg clk;
  reg cin;
  reg [4:1] x;
  reg [4:1] y;

  wire cout;
  wire [4:1] z;

  
  toplevel top1(
    .clk  (clk ) ,
    .x    (x   ) ,
    .y    (y   ) ,
    .cin  (cin ) ,
    .cout (cout) ,
    .z    (z   )
  );

  initial begin 
    $dumpfile("finaltest.vcd");
    $dumpvars(0,tb);
    clk=0;
    x=4'b0000; y=4'b0000; cin=0;
    
    
#3 x = 4'b0010; y = 4'b1110; cin = 0; clk = ~clk; #3 clk = ~clk;
#3 x = 4'b0010; y = 4'b1110; cin = 1; clk = ~clk; #3 clk = ~clk;
#3 x = 4'b0010; y = 4'b1111; cin = 0; clk = ~clk; #3 clk = ~clk;
#3 x = 4'b0010; y = 4'b1111; cin = 1; clk = ~clk; #3 clk = ~clk;

#3 x = 4'b0011; y = 4'b0000; cin = 0; clk = ~clk; #3 clk = ~clk;
#3 x = 4'b0011; y = 4'b0000; cin = 1; clk = ~clk; #3 clk = ~clk;
#3 x = 4'b0011; y = 4'b0001; cin = 0; clk = ~clk; #3 clk = ~clk;
#3 x = 4'b0011; y = 4'b0001; cin = 1; clk = ~clk; #3 clk = ~clk;

#3 x = 4'b0011; y = 4'b0010; cin = 0; clk = ~clk; #3 clk = ~clk;
#3 x = 4'b0011; y = 4'b0010; cin = 1; clk = ~clk; #3 clk = ~clk;
#3 x = 4'b0011; y = 4'b0011; cin = 0; clk = ~clk; #3 clk = ~clk;
#3 x = 4'b0011; y = 4'b0011; cin = 1; clk = ~clk; #3 clk = ~clk;

#3 x = 4'b0011; y = 4'b0100; cin = 0; clk = ~clk; #3 clk = ~clk;
#3 x = 4'b0011; y = 4'b0100; cin = 1; clk = ~clk; #3 clk = ~clk;
#3 x = 4'b0011; y = 4'b0101; cin = 0; clk = ~clk; #3 clk = ~clk;
#3 x = 4'b0011; y = 4'b0101; cin = 1; clk = ~clk; #3 clk = ~clk;

#3 x = 4'b0011; y = 4'b0110; cin = 0; clk = ~clk; #3 clk = ~clk;
#3 x = 4'b0011; y = 4'b0110; cin = 1; clk = ~clk; #3 clk = ~clk;
#3 x = 4'b0011; y = 4'b0111; cin = 0; clk = ~clk; #3 clk = ~clk;
#3 x = 4'b0011; y = 4'b0111; cin = 1; clk = ~clk; #3 clk = ~clk;

#3 x = 4'b0011; y = 4'b1000; cin = 0; clk = ~clk; #3 clk = ~clk;
#3 x = 4'b0011; y = 4'b1000; cin = 1; clk = ~clk; #3 clk = ~clk;
#3 x = 4'b0011; y = 4'b1001; cin = 0; clk = ~clk; #3 clk = ~clk;
#3 x = 4'b0011; y = 4'b1001; cin = 1; clk = ~clk; #3 clk = ~clk;

#3 x = 4'b0011; y = 4'b1010; cin = 0; clk = ~clk; #3 clk = ~clk;
#3 x = 4'b0011; y = 4'b1010; cin = 1; clk = ~clk; #3 clk = ~clk;

    
#3 clk=~clk;#3 clk=~clk;
end 
  
initial 
	$monitor("clk=%b x=%b y=%b cin=%b cout=%b z=%b",clk,x,y,cin,cout,z);
endmodule

project/verilog/finaltest.vcd
$date
	Wed Nov 20 17:03:51 2024
$end
$version
	Icarus Verilog
$end
$timescale
	1ps
$end
$scope module tb $end
$var wire 4 ! z [4:1] $end
$var wire 1 " cout $end
$var reg 1 # cin $end
$var reg 1 $ clk $end
$var reg 4 % x [4:1] $end
$var reg 4 & y [4:1] $end
$scope module top1 $end
$var wire 1 # cin $end
$var wire 1 $ clk $end
$var wire 4 ' x [4:1] $end
$var wire 4 ( y [4:1] $end
$var wire 1 ) z4o $end
$var wire 1 * z3o $end
$var wire 1 + z2o $end
$var wire 1 , z1o $end
$var wire 4 - z [4:1] $end
$var wire 1 . y4in $end
$var wire 1 / y3in $end
$var wire 1 0 y2in $end
$var wire 1 1 y1in $end
$var wire 1 2 x4in $end
$var wire 1 3 x3in $end
$var wire 1 4 x2in $end
$var wire 1 5 x1in $end
$var wire 1 6 coutoo $end
$var wire 1 " cout $end
$var wire 1 7 cinin $end
$scope module cla1 $end
$var wire 1 8 c1 $end
$var wire 1 9 c2 $end
$var wire 1 : c3 $end
$var wire 1 6 cout $end
$var wire 1 , z1 $end
$var wire 1 + z2 $end
$var wire 1 * z3 $end
$var wire 1 ) z4 $end
$var wire 1 . y4 $end
$var wire 1 / y3 $end
$var wire 1 0 y2 $end
$var wire 1 1 y1 $end
$var wire 1 2 x4 $end
$var wire 1 3 x3 $end
$var wire 1 4 x2 $end
$var wire 1 5 x1 $end
$var wire 1 ; p4 $end
$var wire 1 < p3 $end
$var wire 1 = p2 $end
$var wire 1 > p1 $end
$var wire 1 ? g4 $end
$var wire 1 @ g3 $end
$var wire 1 A g2 $end
$var wire 1 B g1 $end
$var wire 1 7 cin $end
$scope module pg1 $end
$var wire 1 B g $end
$var wire 1 > p $end
$var wire 1 1 y $end
$var wire 1 5 x $end
$upscope $end
$scope module pg2 $end
$var wire 1 A g $end
$var wire 1 = p $end
$var wire 1 0 y $end
$var wire 1 4 x $end
$upscope $end
$scope module pg3 $end
$var wire 1 @ g $end
$var wire 1 < p $end
$var wire 1 / y $end
$var wire 1 3 x $end
$upscope $end
$scope module pg4 $end
$var wire 1 ? g $end
$var wire 1 ; p $end
$var wire 1 . y $end
$var wire 1 2 x $end
$upscope $end
$upscope $end
$scope module ffcin $end
$var wire 1 # D $end
$var wire 1 C Dnot $end
$var wire 1 7 Q $end
$var wire 1 D Qbar $end
$var wire 1 $ clk $end
$var wire 1 E clknot $end
$var wire 1 F o1 $end
$var wire 1 G o2 $end
$var wire 1 H o3 $end
$var wire 1 I o4 $end
$var wire 1 J o5 $end
$var wire 1 K o6 $end
$upscope $end
$scope module ffcout $end
$var wire 1 6 D $end
$var wire 1 L Dnot $end
$var wire 1 " Q $end
$var wire 1 M Qbar $end
$var wire 1 $ clk $end
$var wire 1 N clknot $end
$var wire 1 O o1 $end
$var wire 1 P o2 $end
$var wire 1 Q o3 $end
$var wire 1 R o4 $end
$var wire 1 S o5 $end
$var wire 1 T o6 $end
$upscope $end
$scope module ffx1 $end
$var wire 1 U D $end
$var wire 1 V Dnot $end
$var wire 1 5 Q $end
$var wire 1 W Qbar $end
$var wire 1 $ clk $end
$var wire 1 X clknot $end
$var wire 1 Y o1 $end
$var wire 1 Z o2 $end
$var wire 1 [ o3 $end
$var wire 1 \ o4 $end
$var wire 1 ] o5 $end
$var wire 1 ^ o6 $end
$upscope $end
$scope module ffx2 $end
$var wire 1 _ D $end
$var wire 1 ` Dnot $end
$var wire 1 4 Q $end
$var wire 1 a Qbar $end
$var wire 1 $ clk $end
$var wire 1 b clknot $end
$var wire 1 c o1 $end
$var wire 1 d o2 $end
$var wire 1 e o3 $end
$var wire 1 f o4 $end
$var wire 1 g o5 $end
$var wire 1 h o6 $end
$upscope $end
$scope module ffx3 $end
$var wire 1 i D $end
$var wire 1 j Dnot $end
$var wire 1 3 Q $end
$var wire 1 k Qbar $end
$var wire 1 $ clk $end
$var wire 1 l clknot $end
$var wire 1 m o1 $end
$var wire 1 n o2 $end
$var wire 1 o o3 $end
$var wire 1 p o4 $end
$var wire 1 q o5 $end
$var wire 1 r o6 $end
$upscope $end
$scope module ffx4 $end
$var wire 1 s D $end
$var wire 1 t Dnot $end
$var wire 1 2 Q $end
$var wire 1 u Qbar $end
$var wire 1 $ clk $end
$var wire 1 v clknot $end
$var wire 1 w o1 $end
$var wire 1 x o2 $end
$var wire 1 y o3 $end
$var wire 1 z o4 $end
$var wire 1 { o5 $end
$var wire 1 | o6 $end
$upscope $end
$scope module ffy1 $end
$var wire 1 } D $end
$var wire 1 ~ Dnot $end
$var wire 1 1 Q $end
$var wire 1 !" Qbar $end
$var wire 1 $ clk $end
$var wire 1 "" clknot $end
$var wire 1 #" o1 $end
$var wire 1 $" o2 $end
$var wire 1 %" o3 $end
$var wire 1 &" o4 $end
$var wire 1 '" o5 $end
$var wire 1 (" o6 $end
$upscope $end
$scope module ffy2 $end
$var wire 1 )" D $end
$var wire 1 *" Dnot $end
$var wire 1 0 Q $end
$var wire 1 +" Qbar $end
$var wire 1 $ clk $end
$var wire 1 ," clknot $end
$var wire 1 -" o1 $end
$var wire 1 ." o2 $end
$var wire 1 /" o3 $end
$var wire 1 0" o4 $end
$var wire 1 1" o5 $end
$var wire 1 2" o6 $end
$upscope $end
$scope module ffy3 $end
$var wire 1 3" D $end
$var wire 1 4" Dnot $end
$var wire 1 / Q $end
$var wire 1 5" Qbar $end
$var wire 1 $ clk $end
$var wire 1 6" clknot $end
$var wire 1 7" o1 $end
$var wire 1 8" o2 $end
$var wire 1 9" o3 $end
$var wire 1 :" o4 $end
$var wire 1 ;" o5 $end
$var wire 1 <" o6 $end
$upscope $end
$scope module ffy4 $end
$var wire 1 =" D $end
$var wire 1 >" Dnot $end
$var wire 1 . Q $end
$var wire 1 ?" Qbar $end
$var wire 1 $ clk $end
$var wire 1 @" clknot $end
$var wire 1 A" o1 $end
$var wire 1 B" o2 $end
$var wire 1 C" o3 $end
$var wire 1 D" o4 $end
$var wire 1 E" o5 $end
$var wire 1 F" o6 $end
$upscope $end
$scope module ffz1 $end
$var wire 1 , D $end
$var wire 1 G" Dnot $end
$var wire 1 H" Q $end
$var wire 1 I" Qbar $end
$var wire 1 $ clk $end
$var wire 1 J" clknot $end
$var wire 1 K" o1 $end
$var wire 1 L" o2 $end
$var wire 1 M" o3 $end
$var wire 1 N" o4 $end
$var wire 1 O" o5 $end
$var wire 1 P" o6 $end
$upscope $end
$scope module ffz2 $end
$var wire 1 + D $end
$var wire 1 Q" Dnot $end
$var wire 1 R" Q $end
$var wire 1 S" Qbar $end
$var wire 1 $ clk $end
$var wire 1 T" clknot $end
$var wire 1 U" o1 $end
$var wire 1 V" o2 $end
$var wire 1 W" o3 $end
$var wire 1 X" o4 $end
$var wire 1 Y" o5 $end
$var wire 1 Z" o6 $end
$upscope $end
$scope module ffz3 $end
$var wire 1 * D $end
$var wire 1 [" Dnot $end
$var wire 1 \" Q $end
$var wire 1 ]" Qbar $end
$var wire 1 $ clk $end
$var wire 1 ^" clknot $end
$var wire 1 _" o1 $end
$var wire 1 `" o2 $end
$var wire 1 a" o3 $end
$var wire 1 b" o4 $end
$var wire 1 c" o5 $end
$var wire 1 d" o6 $end
$upscope $end
$scope module ffz4 $end
$var wire 1 ) D $end
$var wire 1 e" Dnot $end
$var wire 1 f" Q $end
$var wire 1 g" Qbar $end
$var wire 1 $ clk $end
$var wire 1 h" clknot $end
$var wire 1 i" o1 $end
$var wire 1 j" o2 $end
$var wire 1 k" o3 $end
$var wire 1 l" o4 $end
$var wire 1 m" o5 $end
$var wire 1 n" o6 $end
$upscope $end
$upscope $end
$upscope $end
$enddefinitions $end
#0
$dumpvars
1n"
1m"
xl"
xk"
xj"
xi"
1h"
xg"
xf"
xe"
1d"
1c"
xb"
xa"
x`"
x_"
1^"
x]"
x\"
x["
1Z"
1Y"
xX"
xW"
xV"
xU"
1T"
xS"
xR"
xQ"
1P"
1O"
xN"
xM"
xL"
xK"
1J"
xI"
xH"
xG"
xF"
xE"
xD"
xC"
1B"
1A"
1@"
x?"
1>"
0="
x<"
x;"
x:"
x9"
18"
17"
16"
x5"
14"
03"
x2"
x1"
x0"
x/"
1."
1-"
1,"
x+"
1*"
0)"
x("
x'"
x&"
x%"
1$"
1#"
1""
x!"
1~
0}
x|
x{
xz
xy
1x
1w
1v
xu
1t
0s
xr
xq
xp
xo
1n
1m
1l
xk
1j
0i
xh
xg
xf
xe
1d
1c
1b
xa
1`
0_
x^
x]
x\
x[
1Z
1Y
1X
xW
1V
0U
1T
1S
xR
xQ
xP
xO
1N
xM
xL
xK
xJ
xI
xH
1G
1F
1E
xD
1C
xB
xA
x@
x?
x>
x=
x<
x;
x:
x9
x8
x7
x6
x5
x4
x3
x2
x1
x0
x/
x.
bx -
x,
x+
x*
x)
b0 (
b0 '
b0 &
b0 %
0$
0#
x"
bx !
$end
#3000
0H
0[
0o
0y
0%"
1I
1\
1e
0f
1p
1z
1&"
1/"
00"
19"
0:"
1C"
0D"
1J
1K
1O
1P
1]
1^
1g
1h
1q
1r
1{
1|
1'"
1("
11"
12"
1;"
1<"
1E"
1F"
1K"
1L"
1U"
1V"
1_"
1`"
1i"
1j"
0G
xS
xT
0Z
0c
1d
0n
0x
0$"
0-"
1."
07"
18"
0A"
1B"
xO"
xP"
xY"
xZ"
xc"
xd"
xm"
xn"
0*"
04"
0>"
0`
0E
0N
0X
0b
0l
0v
0""
0,"
06"
0@"
0J"
0T"
0^"
0h"
1)"
13"
1="
1_
1$
b1110 &
b1110 (
b10 %
b10 '
#6000
0k"
0R
0W"
0a"
1Q
1l"
0M"
1X"
1b"
1N"
0L
16
1e"
0)
1Q"
1["
1:
0+
1G"
0*
08
0,
1<
0@
1;
0?
0>
0B
07
05
0a
03
02
01
0+"
19
05"
0?"
0=
1A
1D
1W
14
1k
1u
1!"
10
1/
1.
0K
0O
1P
0^
0g
0r
0|
0("
01"
0;"
0E"
1K"
0L"
1U"
0V"
1_"
0`"
1i"
0j"
1G
1S
1T
1Z
1c
1n
1x
1$"
1-"
17"
1A"
1O"
1P"
1Y"
1Z"
1c"
1d"
1m"
1n"
1E
1N
1X
1b
1l
1v
1""
1,"
16"
1@"
1J"
1T"
1^"
1h"
0$
#9000
0M
0H"
0R"
0\"
b0 !
b0 -
0f"
0I
1"
1I"
1S"
1]"
1g"
1H
1K
1O
1^
1g
1r
1|
1("
11"
1;"
1E"
1L"
1V"
1`"
1j"
0S
0Z
0c
0n
0x
0$"
0-"
07"
0A"
0P"
0Z"
0d"
0n"
0F
0E
0N
0X
0b
0l
0v
0""
0,"
06"
0@"
0J"
0T"
0^"
0h"
0C
1$
1#
#12000
0N"
1M"
0K"
0D
0G"
1,
17
0J
0O
0^
0g
0r
0|
0("
01"
0;"
0E"
1L"
0V"
0`"
0j"
1F
1S
1Z
1c
1n
1x
1$"
1-"
17"
1A"
1P"
1Z"
1d"
1n"
1E
1N
1X
1b
1l
1v
1""
1,"
16"
1@"
1J"
1T"
1^"
1h"
0$
#15000
0H
0I"
0&"
1I
1%"
b1 !
b1 -
1H"
1J
1O
1^
1g
1r
1|
1("
11"
1;"
1E"
1K"
1V"
1`"
1j"
0G
0S
0Z
0c
0n
0x
0#"
1$"
0-"
07"
0A"
0O"
0Z"
0d"
0n"
0~
0E
0N
0X
0b
0l
0v
0""
0,"
06"
0@"
0J"
0T"
0^"
0h"
1C
1}
1$
0#
b1111 &
b1111 (
#18000
1X"
0W"
0N"
1U"
1L"
1Q"
0+
0G"
08
07
0!"
1,
1>
1D
11
0K
0O
0^
0g
0r
0|
0'"
01"
0;"
0E"
0K"
0V"
0`"
0j"
1G
1S
1Z
1c
1n
1x
1#"
1-"
17"
1A"
1O"
1Z"
1d"
1n"
1E
1N
1X
1b
1l
1v
1""
1,"
16"
1@"
1J"
1T"
1^"
1h"
0$
#21000
0I
1H
1K
1O
1^
1g
1r
1|
1'"
11"
1;"
1E"
1K"
1V"
1`"
1j"
0S
0Z
0c
0n
0x
0#"
0-"
07"
0A"
0O"
0Z"
0d"
0n"
0F
0E
0N
0X
0b
0l
0v
0""
0,"
06"
0@"
0J"
0T"
0^"
0h"
0C
1$
1#
#24000
0M"
0X"
1W"
1N"
0U"
0L"
0Q"
1+
0D
1G"
18
0,
17
0J
0O
0^
0g
0r
0|
0'"
01"
0;"
0E"
1K"
1V"
0`"
0j"
1F
1S
1Z
1c
1n
1x
1#"
1-"
17"
1A"
1O"
1Z"
1d"
1n"
1E
1N
1X
1b
1l
1v
1""
1,"
16"
1@"
1J"
1T"
1^"
1h"
0$
#27000
0%"
0/"
09"
0C"
0H
0H"
0S"
1&"
10"
1:"
1D"
0\
1I
1[
1I"
b10 !
b10 -
1R"
0$"
0."
08"
0B"
1J
1O
1^
1g
1r
1|
1'"
11"
1;"
1E"
1L"
1U"
1`"
1j"
0G
0S
0Y
1Z
0c
0n
0x
0P"
0Y"
0d"
0n"
1~
1*"
14"
1>"
0V
0E
0N
0X
0b
0l
0v
0""
0,"
06"
0@"
0J"
0T"
0^"
0h"
1C
0}
0)"
03"
0="
1U
1$
0#
b0 &
b0 (
b11 %
b11 '
#30000
0Q
1R
1b"
1l"
0a"
0k"
0P
0N"
1M"
1_"
1i"
1L
1["
0:
1e"
06
0K"
09
0*
0)
0G"
08
1=
0A
0<
0;
07
0W
1,
01
00
0/
0.
1>
0B
1D
15
1!"
1+"
15"
1?"
0K
1O
0]
0g
0r
0|
0("
02"
0<"
0F"
1L"
0U"
0`"
0j"
1G
1S
1Y
1c
1n
1x
1$"
1."
18"
1B"
1P"
1Y"
1d"
1n"
1E
1N
1X
1b
1l
1v
1""
1,"
16"
1@"
1J"
1T"
1^"
1h"
0$
#33000
0"
0I"
0I
1M
b11 !
b11 -
1H"
1H
1K
1P
1]
1g
1r
1|
1("
12"
1<"
1F"
1K"
1U"
1`"
1j"
0T
0Y
0c
0n
0x
0$"
0."
08"
0B"
0O"
0Y"
0d"
0n"
0F
0E
0N
0X
0b
0l
0v
0""
0,"
06"
0@"
0J"
0T"
0^"
0h"
0C
1$
1#
#36000
0b"
0W"
1a"
0M"
1X"
0_"
1N"
0["
0V"
1*
0L"
19
1Q"
0+
0D
1G"
18
0,
17
0J
0P
0]
0g
0r
0|
0("
02"
0<"
0F"
1K"
1U"
1`"
0j"
1F
1T
1Y
1c
1n
1x
1$"
1."
18"
1B"
1O"
1Y"
1d"
1n"
1E
1N
1X
1b
1l
1v
1""
1,"
16"
1@"
1J"
1T"
1^"
1h"
0$
#39000
0H
0H"
0R"
0]"
0&"
1I
1%"
1I"
1S"
b100 !
b100 -
1\"
1J
1P
1]
1g
1r
1|
1("
12"
1<"
1F"
1L"
1V"
1_"
1j"
0G
0T
0Y
0c
0n
0x
0#"
1$"
0."
08"
0B"
0P"
0Z"
0c"
0n"
0~
0E
0N
0X
0b
0l
0v
0""
0,"
06"
0@"
0J"
0T"
0^"
0h"
1C
1}
1$
0#
b1 &
b1 (
#42000
1N"
0M"
1K"
1G"
07
0!"
0,
0>
1B
1D
11
0K
0P
0]
0g
0r
0|
0'"
02"
0<"
0F"
0L"
0V"
0_"
0j"
1G
1T
1Y
1c
1n
1x
1#"
1."
18"
1B"
1P"
1Z"
1c"
1n"
1E
1N
1X
1b
1l
1v
1""
1,"
16"
1@"
1J"
1T"
1^"
1h"
0$
#45000
0I
1H
1K
1P
1]
1g
1r
1|
1'"
12"
1<"
1F"
1L"
1V"
1_"
1j"
0T
0Y
0c
0n
0x
0#"
0."
08"
0B"
0P"
0Z"
0c"
0n"
0F
0E
0N
0X
0b
0l
0v
0""
0,"
06"
0@"
0J"
0T"
0^"
0h"
0C
1$
1#
#48000
0N"
1M"
0K"
0D
0G"
1,
17
0J
0P
0]
0g
0r
0|
0'"
02"
0<"
0F"
1L"
0V"
0_"
0j"
1F
1T
1Y
1c
1n
1x
1#"
1."
18"
1B"
1P"
1Z"
1c"
1n"
1E
1N
1X
1b
1l
1v
1""
1,"
16"
1@"
1J"
1T"
1^"
1h"
0$
#51000
0%"
0H
0I"
1&"
00"
1I
1/"
b101 !
b101 -
1H"
0$"
1J
1P
1]
1g
1r
1|
1'"
12"
1<"
1F"
1K"
1V"
1_"
1j"
0G
0T
0Y
0c
0n
0x
0-"
1."
08"
0B"
0O"
0Z"
0c"
0n"
1~
0*"
0E
0N
0X
0b
0l
0v
0""
0,"
06"
0@"
0J"
0T"
0^"
0h"
1C
0}
1)"
1$
0#
b10 &
b10 (
#54000
1X"
0W"
08
1U"
1>
0B
1Q"
07
01
0+"
0+
0=
1A
1D
1!"
10
0K
0P
0]
0g
0r
0|
0("
01"
0<"
0F"
0K"
0V"
0_"
0j"
1G
1T
1Y
1c
1n
1x
1$"
1-"
18"
1B"
1O"
1Z"
1c"
1n"
1E
1N
1X
1b
1l
1v
1""
1,"
16"
1@"
1J"
1T"
1^"
1h"
0$
#57000
0I
1H
1K
1P
1]
1g
1r
1|
1("
11"
1<"
1F"
1K"
1V"
1_"
1j"
0T
0Y
0c
0n
0x
0$"
0-"
08"
0B"
0O"
0Z"
0c"
0n"
0F
0E
0N
0X
0b
0l
0v
0""
0,"
06"
0@"
0J"
0T"
0^"
0h"
0C
1$
1#
#60000
0M"
0X"
1W"
1N"
0U"
0L"
0Q"
1+
0D
1G"
18
0,
17
0J
0P
0]
0g
0r
0|
0("
01"
0<"
0F"
1K"
1V"
0_"
0j"
1F
1T
1Y
1c
1n
1x
1$"
1-"
18"
1B"
1O"
1Z"
1c"
1n"
1E
1N
1X
1b
1l
1v
1""
1,"
16"
1@"
1J"
1T"
1^"
1h"
0$
#63000
0H
0H"
0S"
0&"
1I
1%"
1I"
b110 !
b110 -
1R"
1J
1P
1]
1g
1r
1|
1("
11"
1<"
1F"
1L"
1U"
1_"
1j"
0G
0T
0Y
0c
0n
0x
0#"
1$"
0-"
08"
0B"
0P"
0Y"
0c"
0n"
0~
0E
0N
0X
0b
0l
0v
0""
0,"
06"
0@"
0J"
0T"
0^"
0h"
1C
1}
1$
0#
b11 &
b11 (
#66000
1N"
0M"
1K"
1G"
07
0!"
0,
0>
1B
1D
11
0K
0P
0]
0g
0r
0|
0'"
01"
0<"
0F"
0L"
0U"
0_"
0j"
1G
1T
1Y
1c
1n
1x
1#"
1-"
18"
1B"
1P"
1Y"
1c"
1n"
1E
1N
1X
1b
1l
1v
1""
1,"
16"
1@"
1J"
1T"
1^"
1h"
0$
#69000
0I
1H
1K
1P
1]
1g
1r
1|
1'"
11"
1<"
1F"
1L"
1U"
1_"
1j"
0T
0Y
0c
0n
0x
0#"
0-"
08"
0B"
0P"
0Y"
0c"
0n"
0F
0E
0N
0X
0b
0l
0v
0""
0,"
06"
0@"
0J"
0T"
0^"
0h"
0C
1$
1#
#72000
0N"
1M"
0K"
0D
0G"
1,
17
0J
0P
0]
0g
0r
0|
0'"
01"
0<"
0F"
1L"
0U"
0_"
0j"
1F
1T
1Y
1c
1n
1x
1#"
1-"
18"
1B"
1P"
1Y"
1c"
1n"
1E
1N
1X
1b
1l
1v
1""
1,"
16"
1@"
1J"
1T"
1^"
1h"
0$
#75000
0%"
0/"
0H
0I"
1&"
10"
0:"
1I
19"
b111 !
b111 -
1H"
0$"
0."
1J
1P
1]
1g
1r
1|
1'"
11"
1<"
1F"
1K"
1U"
1_"
1j"
0G
0T
0Y
0c
0n
0x
07"
18"
0B"
0O"
0Y"
0c"
0n"
1~
1*"
04"
0E
0N
0X
0b
0l
0v
0""
0,"
06"
0@"
0J"
0T"
0^"
0h"
1C
0}
0)"
13"
1$
0#
b100 &
b100 (
#78000
1a"
0X"
1l"
0k"
1V"
0b"
1i"
0Q"
1`"
1e"
08
1+
09
0)
1>
0B
1=
0A
0["
0:
07
01
00
05"
1*
1<
1D
1!"
1+"
1/
0K
0P
0]
0g
0r
0|
0("
02"
0;"
0F"
0K"
0U"
0_"
0j"
1G
1T
1Y
1c
1n
1x
1$"
1."
17"
1B"
1O"
1Y"
1c"
1n"
1E
1N
1X
1b
1l
1v
1""
1,"
16"
1@"
1J"
1T"
1^"
1h"
0$
#81000
0I
1H
1K
1P
1]
1g
1r
1|
1("
12"
1;"
1F"
1K"
1U"
1_"
1j"
0T
0Y
0c
0n
0x
0$"
0."
07"
0B"
0O"
0Y"
0c"
0n"
0F
0E
0N
0X
0b
0l
0v
0""
0,"
06"
0@"
0J"
0T"
0^"
0h"
0C
1$
1#
#84000
0l"
0a"
1k"
1b"
0W"
0i"
0M"
0e"
0`"
1X"
1)
1N"
1:
1["
0V"
0*
0L"
19
1Q"
0+
0D
1G"
18
0,
17
0J
0P
0]
0g
0r
0|
0("
02"
0;"
0F"
1K"
1U"
1_"
1j"
1F
1T
1Y
1c
1n
1x
1$"
1."
17"
1B"
1O"
1Y"
1c"
1n"
1E
1N
1X
1b
1l
1v
1""
1,"
16"
1@"
1J"
1T"
1^"
1h"
0$
#87000
0H
0H"
0R"
0\"
0g"
0&"
1I
1%"
1I"
1S"
1]"
b1000 !
b1000 -
1f"
1J
1P
1]
1g
1r
1|
1("
12"
1;"
1F"
1L"
1V"
1`"
1i"
0G
0T
0Y
0c
0n
0x
0#"
1$"
0."
07"
0B"
0P"
0Z"
0d"
0m"
0~
0E
0N
0X
0b
0l
0v
0""
0,"
06"
0@"
0J"
0T"
0^"
0h"
1C
1}
1$
0#
b101 &
b101 (
#90000
1N"
0M"
1K"
1G"
07
0!"
0,
0>
1B
1D
11
0K
0P
0]
0g
0r
0|
0'"
02"
0;"
0F"
0L"
0V"
0`"
0i"
1G
1T
1Y
1c
1n
1x
1#"
1."
17"
1B"
1P"
1Z"
1d"
1m"
1E
1N
1X
1b
1l
1v
1""
1,"
16"
1@"
1J"
1T"
1^"
1h"
0$
#93000
0I
1H
1K
1P
1]
1g
1r
1|
1'"
12"
1;"
1F"
1L"
1V"
1`"
1i"
0T
0Y
0c
0n
0x
0#"
0."
07"
0B"
0P"
0Z"
0d"
0m"
0F
0E
0N
0X
0b
0l
0v
0""
0,"
06"
0@"
0J"
0T"
0^"
0h"
0C
1$
1#
