project/verilog/flipflop.v
`timescale 1ns / 1ps

module ffo(D, clk, Q, Qbar);

  input D; 
  input clk; 
  output Q;
  output Qbar;

  wire clknot, Dnot, o1, o2, o3, o4, o5, o6;

  assign clknot = ~clk;
  assign Dnot = ~D;
  assign o1 = ~(D & clknot);
  assign o2 = ~(Dnot & clknot);
  assign o3 = ~(o1 & o4);
  assign o4 = ~(o2 & o3);
  assign o5 = ~(o3 & clk);
  assign o6 = ~(o4 & clk);
  assign Q = ~(o5 & Qbar);
  assign Qbar = ~(o6 & Q);

endmodule

module ffi(D, clk, Q, Qbar);

  input D; 
  input clk; 
  output Q;
  output Qbar;

  wire clknot, Dnot, o1, o2, o3, o4, o5, o6;

  assign clknot = ~clk;
  assign Dnot = ~D;
  assign o1 = ~(D & clk);
  assign o2 = ~(Dnot & clk);
  assign o3 = ~(o1 & o4);
  assign o4 = ~(o2 & o3);
  assign o5 = ~(o3 & clknot);
  assign o6 = ~(o4 & clknot);
  assign Q = ~(o5 & Qbar);
  assign Qbar = ~(o6 & Q);

endmodule

module ff(D, clk, Q, Qbar);

  input D; 
  input clk; 
  output Q;
  output Qbar;

  wire clknot, Dnot, o1, o2, o3, o4, o5, o6;

  assign clknot = ~clk;
  assign Dnot = ~D;
  assign o1 = ~(D & clk);
  assign o2 = ~(Dnot & clk);
  assign o3 = ~(o1 & o4);
  assign o4 = ~(o2 & o3);
  assign o5 = ~(o3 & clk);
  assign o6 = ~(o4 & clk);
  assign Q = ~(o5 & Qbar);
  assign Qbar = ~(o6 & Q);

endmodule

project/verilog/flipflop_tb.v

`timescale 1ns / 1ps

module flipfloptb;

  reg D;
  reg clk;
	
  wire Q1;
  wire Qbar1;


  ff d0 (
    .D(D),
    .clk(clk),
    .Q(Q1),
    .Qbar(Qbar1)
  );



  initial begin 
    $dumpfile("flipflop.vcd");
    $dumpvars(0,flipfloptb);
    clk=0;
    D=0;

    #10 clk  =~clk;
        D=1;
    #10 clk  =~clk;
    #10 clk  =~clk;
        D=0;
    #10 clk  =~clk;
    #10 clk  =~clk;
        D=1;
    #10 clk  =~clk;
    #10 clk  =~clk;
        D=1;
    #10 clk  =~clk;
        D=0;
    #10 clk  =~clk;
        D=1;
    #10 clk  =~clk;
    #10 clk  =~clk;
    #10 clk  =~clk;
    #10 clk  =~clk;

  end 
  
  initial 
		$monitor("D=%d clk=%d Q1=%d Qbar1=%d",D,clk,Q1,Qbar1);
endmodule

project/verilog/flipflop.vcd
$date
	Wed Nov 20 16:58:30 2024
$end
$version
	Icarus Verilog
$end
$timescale
	1ps
$end
$scope module flipfloptb $end
$var wire 1 ! Qbar1 $end
$var wire 1 " Q1 $end
$var reg 1 # D $end
$var reg 1 $ clk $end
$scope module d0 $end
$var wire 1 # D $end
$var wire 1 % Dnot $end
$var wire 1 " Q $end
$var wire 1 ! Qbar $end
$var wire 1 $ clk $end
$var wire 1 & clknot $end
$var wire 1 ' o1 $end
$var wire 1 ( o2 $end
$var wire 1 ) o3 $end
$var wire 1 * o4 $end
$var wire 1 + o5 $end
$var wire 1 , o6 $end
$upscope $end
$upscope $end
$enddefinitions $end
#0
$dumpvars
1,
1+
x*
x)
1(
1'
1&
1%
0$
0#
x"
x!
$end
#10000
1"
0!
1)
0*
0'
1(
0+
1,
0%
0&
1#
1$
#20000
1'
1+
1&
0$
#30000
0"
1!
0,
0)
1*
0(
1+
1%
0&
0#
1$
#40000
1(
1,
1&
0$
#50000
0!
1"
0+
0*
1)
0'
1(
1,
0%
0&
1#
1$
#60000
1'
1+
1&
0$
#70000
0'
0+
0&
1$
#80000
1'
1+
1%
1&
0#
0$
#90000
0!
1,
0*
0'
1(
0+
0%
0&
1#
1$
#100000
1'
1+
1&
0$
#110000
0'
0+
0&
1$
#120000
1'
1+
1&
0$
#130000
0'
0+
0&
1$
